README.txt
setup.cfg
setup.py
collective/__init__.py
collective.ads.egg-info/PKG-INFO
collective.ads.egg-info/SOURCES.txt
collective.ads.egg-info/dependency_links.txt
collective.ads.egg-info/entry_points.txt
collective.ads.egg-info/namespace_packages.txt
collective.ads.egg-info/not-zip-safe
collective.ads.egg-info/requires.txt
collective.ads.egg-info/top_level.txt
collective/ads/AppConfig.py
collective/ads/__init__.py
collective/ads/config.py
collective/ads/configure.zcml
collective/ads/profiles.zcml
collective/ads/refresh.txt
collective/ads/setuphandlers.py
collective/ads/tests.py
collective/ads/version.txt
collective/ads/admin/AdsAdmin.py
collective/ads/admin/__init__.py
collective/ads/admin/utility.py
collective/ads/browser/__init__.py
collective/ads/browser/adsadmin.py
collective/ads/browser/configure.zcml
collective/ads/browser/controlpanel.py
collective/ads/browser/interfaces.py
collective/ads/browser/portlet.py
collective/ads/browser/images/adminicon.gif
collective/ads/browser/images/ads.gif
collective/ads/browser/stylesheets/ads_style.css
collective/ads/browser/templates/adsadmin_view.pt
collective/ads/browser/templates/adsportlet.pt
collective/ads/content/Banner.py
collective/ads/content/__init__.py
collective/ads/content/interfaces.py
collective/ads/profiles/default/actionicons.xml
collective/ads/profiles/default/atadsmanager.txt
collective/ads/profiles/default/catalog.xml
collective/ads/profiles/default/componentregistry.xml
collective/ads/profiles/default/controlpanel.xml
collective/ads/profiles/default/cssregistry.xml
collective/ads/profiles/default/factorytool.xml
collective/ads/profiles/default/import_steps.xml
collective/ads/profiles/default/portlets.xml
collective/ads/profiles/default/skins.xml
collective/ads/profiles/default/toolset.xml
collective/ads/profiles/default/types.xml
collective/ads/profiles/default/types/AdsAdmin.xml
collective/ads/profiles/default/types/Banner.xml
collective/ads/profiles/default/types/adsadmin.xml
collective/ads/profiles/default/types/banner.xml
collective/ads/skins/ads_images/README.txt
collective/ads/skins/ads_templates/readme.txt
docs/HISTORY.txt
docs/INSTALL.txt
docs/LICENSE.GPL
docs/LICENSE.txt