Metadata-Version: 1.0
Name: collective.ads
Version: 0.1
Summary: Plone Ads
Home-page: http://svn.plone.org/svn/plone/plone.example
Author: Four Digits
Author-email: maarten@fourdigits.nl
License: GPL
Keywords: Plone Ads
Platform: UNKNOWN
Classifier: Framework :: Plone
Classifier: Programming Language :: Python
Classifier: Topic :: Software Development :: Libraries :: Python Modules
